{
  "auc": 0.8333333333333334,
  "log_loss": 0.5933266319579583,
  "calibration_error": 0.44976517040795,
  "n_train_events": 290,
  "train_date_range": {
    "start": "2023-06-26",
    "end": "2026-04-26"
  },
  "rejected_reason": "",
  "fold_metrics": [
    {
      "auc": 0.5,
      "log_loss": 1.239146129757595,
      "calibration_max_error": 0.6605592057459022,
      "calibration_mean_error": 0.6605592057459022,
      "fold": 3,
      "train_size": 232,
      "test_size": 29,
      "best_iteration": 1
    },
    {
      "auc": 1.0,
      "log_loss": 0.539991761946341,
      "calibration_max_error": 0.6877960819796778,
      "calibration_mean_error": 0.4197137367540255,
      "fold": 4,
      "train_size": 261,
      "test_size": 14,
      "best_iteration": 20
    },
    {
      "auc": 1.0,
      "log_loss": 0.0008420041699391575,
      "calibration_max_error": 0.0009402234982700541,
      "calibration_mean_error": 0.0005704535132678988,
      "fold": 5,
      "train_size": 275,
      "test_size": 15,
      "best_iteration": 200
    }
  ],
  "tier": "per_stock",
  "identifier": "OOREDOO",
  "version": "2026-05-13"
}